nsp/__init__.py
nsp/activations.py
nsp/nngraph.py
nsp/outputLoader.py
nsp/transformer.py
nsp/visualizer.py
nsp-0.0.16.dist-info/LICENSE
nsp-0.0.16.dist-info/METADATA
nsp-0.0.16.dist-info/WHEEL
nsp-0.0.16.dist-info/top_level.txt
nsp-0.0.16.dist-info/RECORD
