Metadata-Version: 2.1
Name: nsp
Version: 0.0.16
Summary: Neural Network Signal Processing
Home-page: UNKNOWN
Author: Felipa Schwarz
License: UNKNOWN
Keywords: python,neural network,analysis,activations,activation pattern,fourier analysis
Platform: UNKNOWN
License-File: LICENSE
Requires-Dist: numpy
Requires-Dist: scipy
Requires-Dist: torch
Requires-Dist: networkx
Requires-Dist: matplotlib
